{
  "bridge": {
    "host": "0.0.0.0",
    "port": 8080,
    "count_threshold": 10,
    "time_threshold": 15,
    "meshtastic_reboot_interval": 3600,
    "meshtastic_port": "COM1",
    "target_device_id": "!12345678",
    "channel": 1
  },
  "client": {
    "meshtastic_port": "COM2",
    "source_device_id": "!abcdefgh",
    "channel": 1
  },
  "sondeHub": {
    "enabled": false,
    "uploader_callsign": "N0CALL",
    "uploader_position": [0.0, 0.0, 0],
    "uploader_antenna": "1/4 wave vertical"
  }
}